{
  "metadata": {
    "source_fichier": "offres_emploi_it_maroc.json",
    "date_ingestion": "2026-05-06T21:12:37.017535",
    "partition": "rekrute/2024_07",
    "nb_offres": 94,
    "pipeline_version": "2.0"
  },
  "offres": [
    {
      "id_offre": "RK-2024-00120",
      "source": "rekrute",
      "titre_poste": "Dev Data",
      "description": "Nous recherchons un profil qualifie. Connaissances exigees : Python / SQL / Spark. Travail en equipe Agile.",
      "competences_brut": "GCP, BigQuery, Airflow",
      "entreprise": "DataWize",
      "ville": "casa",
      "type_contrat": "Freelance",
      "experience_requise": "min 3 ans",
      "salaire_brut": "Selon profil",
      "niveau_etudes": "Bac+3",
      "secteur": "Banque",
      "date_publication": "2024-07-13",
      "date_expiration": "2024-08-12",
      "nb_postes": 3,
      "teletravail": "Hybride",
      "langue_requise": [
        "Français",
        "Anglais"
      ]
    },
    {
      "id_offre": "RK-2024-00134",
      "source": "rekrute",
      "titre_poste": "Dev Data",
      "description": "Nous recherchons un profil qualifie. Connaissances exigees : Python / SQL / Spark. Travail en equipe Agile.",
      "competences_brut": "React, Node.js, PostgreSQL",
      "entreprise": "BankAlMaghrib",
      "ville": "CASABLANCA",
      "type_contrat": "CDI",
      "experience_requise": null,
      "salaire_brut": null,
      "niveau_etudes": "Bac+3",
      "secteur": "Informatique / Télécom",
      "date_publication": "2024-07-22",
      "date_expiration": "2024-08-21",
      "nb_postes": 2,
      "teletravail": "Hybride",
      "langue_requise": [
        "Français",
        "Anglais"
      ]
    },
    {
      "id_offre": "RK-2024-00182",
      "source": "rekrute",
      "titre_poste": "Data Engineer Junior",
      "description": "Nous recherchons un profil qualifie. Connaissances exigees : Power BI, SQL, Excel. Travail en equipe Agile.",
      "competences_brut": "Java, Spring, Angular",
      "entreprise": "TangerMedTech",
      "ville": "Marrakech",
      "type_contrat": "Permanent",
      "experience_requise": "3-5 ans",
      "salaire_brut": "Selon profil",
      "niveau_etudes": "Ingénieur",
      "secteur": "Banque",
      "date_publication": "2024-07-24",
      "date_expiration": "2024-08-23",
      "nb_postes": 1,
      "teletravail": "Remote",
      "langue_requise": [
        "Français",
        "Anglais"
      ]
    },
    {
      "id_offre": "RK-2024-00326",
      "source": "rekrute",
      "titre_poste": "Dev Data",
      "description": "Nous recherchons un profil qualifie. Connaissances exigees : React, Node.js, PostgreSQL. Travail en equipe Agile.",
      "competences_brut": "GCP, BigQuery, Airflow",
      "entreprise": "DataWize",
      "ville": "Rabat",
      "type_contrat": "cdi",
      "experience_requise": "3 à 5 ans",
      "salaire_brut": "Selon profil",
      "niveau_etudes": "Bac+3",
      "secteur": "Banque",
      "date_publication": "2024-07-26",
      "date_expiration": "2024-08-25",
      "nb_postes": 3,
      "teletravail": "Présentiel",
      "langue_requise": [
        "Français",
        "Anglais"
      ]
    },
    {
      "id_offre": "RK-2024-00410",
      "source": "rekrute",
      "titre_poste": "Data Engineer Junior",
      "description": "Nous recherchons un profil qualifie. Connaissances exigees : Power BI, SQL, Excel. Travail en equipe Agile.",
      "competences_brut": "GCP, BigQuery, Airflow",
      "entreprise": "DataWize",
      "ville": "Fès",
      "type_contrat": "CDI",
      "experience_requise": "Senior (7+ ans)",
      "salaire_brut": "Selon profil",
      "niveau_etudes": "Bac+5",
      "secteur": "Conseil",
      "date_publication": "2024-07-06",
      "date_expiration": "2024-08-05",
      "nb_postes": 2,
      "teletravail": "Remote",
      "langue_requise": [
        "Français",
        "Anglais"
      ]
    },
    {
      "id_offre": "RK-2024-00425",
      "source": "rekrute",
      "titre_poste": "Développeur BI",
      "description": "Nous recherchons un profil qualifie. Connaissances exigees : Python / SQL / Spark. Travail en equipe Agile.",
      "competences_brut": "Java, Spring, Angular",
      "entreprise": "Inwi",
      "ville": "Casablanca",
      "type_contrat": "Contrat à durée indéterminée",
      "experience_requise": "Senior (7+ ans)",
      "salaire_brut": "Confidentiel",
      "niveau_etudes": "Bac+3",
      "secteur": "Informatique / Télécom",
      "date_publication": "2024-07-31",
      "date_expiration": "2024-08-30",
      "nb_postes": 2,
      "teletravail": "Hybride",
      "langue_requise": [
        "Français",
        "Anglais"
      ]
    },
    {
      "id_offre": "RK-2024-00589",
      "source": "rekrute",
      "titre_poste": "Développeur BI",
      "description": "Nous recherchons un profil qualifie. Connaissances exigees : React, Node.js, PostgreSQL. Travail en equipe Agile.",
      "competences_brut": "Java, Spring, Angular",
      "entreprise": "TechMaroc SARL",
      "ville": "Marrakech",
      "type_contrat": "Contrat à durée indéterminée",
      "experience_requise": "min 3 ans",
      "salaire_brut": "Selon profil",
      "niveau_etudes": "Bac+5",
      "secteur": "Informatique / Télécom",
      "date_publication": "2024-07-24",
      "date_expiration": "2024-08-23",
      "nb_postes": 2,
      "teletravail": "télétravail",
      "langue_requise": [
        "Français",
        "Anglais"
      ]
    },
    {
      "id_offre": "RK-2024-00600",
      "source": "rekrute",
      "titre_poste": "Data Scientist",
      "description": "Nous recherchons un profil qualifie. Connaissances exigees : Power BI, SQL, Excel. Travail en equipe Agile.",
      "competences_brut": "AWS • Python • Docker",
      "entreprise": "DataWize",
      "ville": "Casablanca",
      "type_contrat": "CDI",
      "experience_requise": "Débutant accepté",
      "salaire_brut": "Confidentiel",
      "niveau_etudes": "Ingénieur",
      "secteur": "Banque",
      "date_publication": "2024-07-03",
      "date_expiration": "2024-08-02",
      "nb_postes": 2,
      "teletravail": "Hybride",
      "langue_requise": [
        "Français",
        "Anglais"
      ]
    },
    {
      "id_offre": "RK-2024-00609",
      "source": "rekrute",
      "titre_poste": "DevOps",
      "description": "Nous recherchons un profil qualifie. Connaissances exigees : Python / SQL / Spark. Travail en equipe Agile.",
      "competences_brut": "React, Node.js, PostgreSQL",
      "entreprise": "TechMaroc SARL",
      "ville": "CASABLANCA",
      "type_contrat": "Contrat à durée indéterminée",
      "experience_requise": null,
      "salaire_brut": "Selon profil",
      "niveau_etudes": "Bac+3",
      "secteur": "Conseil",
      "date_publication": "2024-07-04",
      "date_expiration": "2024-08-03",
      "nb_postes": 1,
      "teletravail": "Hybride",
      "langue_requise": [
        "Français",
        "Anglais"
      ]
    },
    {
      "id_offre": "RK-2024-00616",
      "source": "rekrute",
      "titre_poste": "DevOps",
      "description": "Nous recherchons un profil qualifie. Connaissances exigees : GCP, BigQuery, Airflow. Travail en equipe Agile.",
      "competences_brut": "Java, Spring, Angular",
      "entreprise": "TechMaroc SARL",
      "ville": "Tanger",
      "type_contrat": "Freelance",
      "experience_requise": "Senior (7+ ans)",
      "salaire_brut": "15K-20K",
      "niveau_etudes": "Ingénieur",
      "secteur": "Informatique / Télécom",
      "date_publication": "2024-07-25",
      "date_expiration": "2024-08-24",
      "nb_postes": 1,
      "teletravail": "télétravail",
      "langue_requise": [
        "Français",
        "Anglais"
      ]
    },
    {
      "id_offre": "RK-2024-00617",
      "source": "rekrute",
      "titre_poste": "Dev Data",
      "description": "Nous recherchons un profil qualifie. Connaissances exigees : GCP, BigQuery, Airflow. Travail en equipe Agile.",
      "competences_brut": "GCP, BigQuery, Airflow",
      "entreprise": "TangerMedTech",
      "ville": "Rabat",
      "type_contrat": "Contrat à durée indéterminée",
      "experience_requise": "Débutant accepté",
      "salaire_brut": "15000-20000 MAD",
      "niveau_etudes": "Bac+5",
      "secteur": "Informatique / Télécom",
      "date_publication": "2024-07-08",
      "date_expiration": "2024-08-07",
      "nb_postes": 1,
      "teletravail": "Hybride",
      "langue_requise": [
        "Français",
        "Anglais"
      ]
    },
    {
      "id_offre": "RK-2024-00664",
      "source": "rekrute",
      "titre_poste": "Ingénieur Big Data",
      "description": "Nous recherchons un profil qualifie. Connaissances exigees : Power BI, SQL, Excel. Travail en equipe Agile.",
      "competences_brut": "Java, Spring, Angular",
      "entreprise": "BankAlMaghrib",
      "ville": "CASABLANCA",
      "type_contrat": "Freelance",
      "experience_requise": "min 3 ans",
      "salaire_brut": "Confidentiel",
      "niveau_etudes": "Bac+5",
      "secteur": "Informatique / Télécom",
      "date_publication": "2024-07-09",
      "date_expiration": "2024-08-08",
      "nb_postes": 1,
      "teletravail": "Présentiel",
      "langue_requise": [
        "Français",
        "Anglais"
      ]
    },
    {
      "id_offre": "RK-2024-00703",
      "source": "rekrute",
      "titre_poste": "Développeur BI",
      "description": "Nous recherchons un profil qualifie. Connaissances exigees : GCP, BigQuery, Airflow. Travail en equipe Agile.",
      "competences_brut": "Power BI, SQL, Excel",
      "entreprise": "DataWize",
      "ville": "Fès",
      "type_contrat": "Permanent",
      "experience_requise": "Débutant accepté",
      "salaire_brut": "Confidentiel",
      "niveau_etudes": "Bac+5",
      "secteur": "Conseil",
      "date_publication": "2024-07-11",
      "date_expiration": "2024-08-10",
      "nb_postes": 2,
      "teletravail": "Présentiel",
      "langue_requise": [
        "Français",
        "Anglais"
      ]
    },
    {
      "id_offre": "RK-2024-00713",
      "source": "rekrute",
      "titre_poste": "SysAdmin",
      "description": "Nous recherchons un profil qualifie. Connaissances exigees : React, Node.js, PostgreSQL. Travail en equipe Agile.",
      "competences_brut": "AWS • Python • Docker",
      "entreprise": "DataWize",
      "ville": "Marrakech",
      "type_contrat": "Contrat à durée indéterminée",
      "experience_requise": "Senior (7+ ans)",
      "salaire_brut": null,
      "niveau_etudes": "Bac+3",
      "secteur": "Conseil",
      "date_publication": "2024-07-19",
      "date_expiration": "2024-08-18",
      "nb_postes": 3,
      "teletravail": "télétravail",
      "langue_requise": [
        "Français",
        "Anglais"
      ]
    },
    {
      "id_offre": "RK-2024-00745",
      "source": "rekrute",
      "titre_poste": "Développeur Full Stack React/Node.js",
      "description": "Nous recherchons un profil qualifie. Connaissances exigees : Java, Spring, Angular. Travail en equipe Agile.",
      "competences_brut": "React, Node.js, PostgreSQL",
      "entreprise": "TechMaroc SARL",
      "ville": "Fès",
      "type_contrat": "Contrat à durée indéterminée",
      "experience_requise": "3-5 ans",
      "salaire_brut": "Confidentiel",
      "niveau_etudes": "Ingénieur",
      "secteur": "Informatique / Télécom",
      "date_publication": "2024-07-11",
      "date_expiration": "2024-08-10",
      "nb_postes": 1,
      "teletravail": "télétravail",
      "langue_requise": [
        "Français",
        "Anglais"
      ]
    },
    {
      "id_offre": "RK-2024-00782",
      "source": "rekrute",
      "titre_poste": "SysAdmin",
      "description": "Nous recherchons un profil qualifie. Connaissances exigees : React, Node.js, PostgreSQL. Travail en equipe Agile.",
      "competences_brut": "React, Node.js, PostgreSQL",
      "entreprise": "BankAlMaghrib",
      "ville": "Casablanca",
      "type_contrat": "Contrat à durée indéterminée",
      "experience_requise": "Senior (7+ ans)",
      "salaire_brut": "Selon profil",
      "niveau_etudes": "Bac+5",
      "secteur": "Banque",
      "date_publication": "2024-07-27",
      "date_expiration": "2024-08-26",
      "nb_postes": 3,
      "teletravail": "télétravail",
      "langue_requise": [
        "Français",
        "Anglais"
      ]
    },
    {
      "id_offre": "RK-2024-00791",
      "source": "rekrute",
      "titre_poste": "DevOps",
      "description": "Nous recherchons un profil qualifie. Connaissances exigees : Java, Spring, Angular. Travail en equipe Agile.",
      "competences_brut": "Power BI, SQL, Excel",
      "entreprise": "TangerMedTech",
      "ville": "Casablanca",
      "type_contrat": "CDI",
      "experience_requise": "3 à 5 ans",
      "salaire_brut": "15K-20K",
      "niveau_etudes": "Ingénieur",
      "secteur": "Informatique / Télécom",
      "date_publication": "2024-07-26",
      "date_expiration": "2024-08-25",
      "nb_postes": 2,
      "teletravail": "Présentiel",
      "langue_requise": [
        "Français",
        "Anglais"
      ]
    },
    {
      "id_offre": "RK-2024-00821",
      "source": "rekrute",
      "titre_poste": "Développeur Full Stack React/Node.js",
      "description": "Nous recherchons un profil qualifie. Connaissances exigees : Power BI, SQL, Excel. Travail en equipe Agile.",
      "competences_brut": "AWS • Python • Docker",
      "entreprise": "Inwi",
      "ville": "Tanger",
      "type_contrat": "CDI",
      "experience_requise": "min 3 ans",
      "salaire_brut": "15K-20K",
      "niveau_etudes": "Bac+5",
      "secteur": "Conseil",
      "date_publication": "2024-07-30",
      "date_expiration": "2024-08-29",
      "nb_postes": 2,
      "teletravail": "Hybride",
      "langue_requise": [
        "Français",
        "Anglais"
      ]
    },
    {
      "id_offre": "RK-2024-00840",
      "source": "rekrute",
      "titre_poste": "Data Scientist",
      "description": "Nous recherchons un profil qualifie. Connaissances exigees : GCP, BigQuery, Airflow. Travail en equipe Agile.",
      "competences_brut": "Power BI, SQL, Excel",
      "entreprise": "DataWize",
      "ville": "Casablanca",
      "type_contrat": "CDI",
      "experience_requise": "Débutant accepté",
      "salaire_brut": "Confidentiel",
      "niveau_etudes": "Ingénieur",
      "secteur": "Informatique / Télécom",
      "date_publication": "2024-07-15",
      "date_expiration": "2024-08-14",
      "nb_postes": 1,
      "teletravail": "Présentiel",
      "langue_requise": [
        "Français",
        "Anglais"
      ]
    },
    {
      "id_offre": "RK-2024-00858",
      "source": "rekrute",
      "titre_poste": "Data Eng.",
      "description": "Nous recherchons un profil qualifie. Connaissances exigees : GCP, BigQuery, Airflow. Travail en equipe Agile.",
      "competences_brut": "GCP, BigQuery, Airflow",
      "entreprise": "BankAlMaghrib",
      "ville": "Casablanca",
      "type_contrat": "Contrat à durée indéterminée",
      "experience_requise": "min 3 ans",
      "salaire_brut": "Selon profil",
      "niveau_etudes": "Ingénieur",
      "secteur": "Conseil",
      "date_publication": "2024-07-27",
      "date_expiration": "2024-08-26",
      "nb_postes": 2,
      "teletravail": "Hybride",
      "langue_requise": [
        "Français",
        "Anglais"
      ]
    },
    {
      "id_offre": "RK-2024-00951",
      "source": "rekrute",
      "titre_poste": "DevOps",
      "description": "Nous recherchons un profil qualifie. Connaissances exigees : Power BI, SQL, Excel. Travail en equipe Agile.",
      "competences_brut": "AWS • Python • Docker",
      "entreprise": "TechMaroc SARL",
      "ville": "Marrakech",
      "type_contrat": "Freelance",
      "experience_requise": "Débutant accepté",
      "salaire_brut": "8000-12000 dh",
      "niveau_etudes": "Bac+3",
      "secteur": "Banque",
      "date_publication": "2024-07-14",
      "date_expiration": "2024-08-13",
      "nb_postes": 1,
      "teletravail": "Hybride",
      "langue_requise": [
        "Français",
        "Anglais"
      ]
    },
    {
      "id_offre": "RK-2024-01070",
      "source": "rekrute",
      "titre_poste": "DevOps",
      "description": "Nous recherchons un profil qualifie. Connaissances exigees : AWS • Python • Docker. Travail en equipe Agile.",
      "competences_brut": "GCP, BigQuery, Airflow",
      "entreprise": "Inwi",
      "ville": "Fès",
      "type_contrat": "Permanent",
      "experience_requise": null,
      "salaire_brut": "15K-20K",
      "niveau_etudes": "Ingénieur",
      "secteur": "Conseil",
      "date_publication": "2024-07-09",
      "date_expiration": "2024-08-08",
      "nb_postes": 2,
      "teletravail": "Présentiel",
      "langue_requise": [
        "Français",
        "Anglais"
      ]
    },
    {
      "id_offre": "RK-2024-01093",
      "source": "rekrute",
      "titre_poste": "Data Scientist",
      "description": "Nous recherchons un profil qualifie. Connaissances exigees : GCP, BigQuery, Airflow. Travail en equipe Agile.",
      "competences_brut": "React, Node.js, PostgreSQL",
      "entreprise": "Inwi",
      "ville": "casa",
      "type_contrat": "Contrat à durée indéterminée",
      "experience_requise": "3 à 5 ans",
      "salaire_brut": "Confidentiel",
      "niveau_etudes": "Ingénieur",
      "secteur": "Conseil",
      "date_publication": "2024-07-25",
      "date_expiration": "2024-08-24",
      "nb_postes": 3,
      "teletravail": "Remote",
      "langue_requise": [
        "Français",
        "Anglais"
      ]
    },
    {
      "id_offre": "RK-2024-01195",
      "source": "rekrute",
      "titre_poste": "DevOps",
      "description": "Nous recherchons un profil qualifie. Connaissances exigees : Java, Spring, Angular. Travail en equipe Agile.",
      "competences_brut": "Python / SQL / Spark",
      "entreprise": "TechMaroc SARL",
      "ville": "Casablanca",
      "type_contrat": "Freelance",
      "experience_requise": "min 3 ans",
      "salaire_brut": null,
      "niveau_etudes": "Bac+3",
      "secteur": "Informatique / Télécom",
      "date_publication": "2024-07-11",
      "date_expiration": "2024-08-10",
      "nb_postes": 2,
      "teletravail": "télétravail",
      "langue_requise": [
        "Français",
        "Anglais"
      ]
    },
    {
      "id_offre": "RK-2024-01436",
      "source": "rekrute",
      "titre_poste": "Data Eng.",
      "description": "Nous recherchons un profil qualifie. Connaissances exigees : GCP, BigQuery, Airflow. Travail en equipe Agile.",
      "competences_brut": "AWS • Python • Docker",
      "entreprise": "DataWize",
      "ville": "CASABLANCA",
      "type_contrat": "Permanent",
      "experience_requise": "Senior (7+ ans)",
      "salaire_brut": "15K-20K",
      "niveau_etudes": "Bac+3",
      "secteur": "Conseil",
      "date_publication": "2024-07-09",
      "date_expiration": "2024-08-08",
      "nb_postes": 2,
      "teletravail": "Remote",
      "langue_requise": [
        "Français",
        "Anglais"
      ]
    },
    {
      "id_offre": "RK-2024-01478",
      "source": "rekrute",
      "titre_poste": "Ingénieur Big Data",
      "description": "Nous recherchons un profil qualifie. Connaissances exigees : GCP, BigQuery, Airflow. Travail en equipe Agile.",
      "competences_brut": "Java, Spring, Angular",
      "entreprise": "Inwi",
      "ville": "Casablanca",
      "type_contrat": "Permanent",
      "experience_requise": "3 à 5 ans",
      "salaire_brut": "15K-20K",
      "niveau_etudes": "Bac+5",
      "secteur": "Banque",
      "date_publication": "2024-07-19",
      "date_expiration": "2024-08-18",
      "nb_postes": 2,
      "teletravail": "Hybride",
      "langue_requise": [
        "Français",
        "Anglais"
      ]
    },
    {
      "id_offre": "RK-2024-01526",
      "source": "rekrute",
      "titre_poste": "DevOps",
      "description": "Nous recherchons un profil qualifie. Connaissances exigees : Java, Spring, Angular. Travail en equipe Agile.",
      "competences_brut": "GCP, BigQuery, Airflow",
      "entreprise": "DataWize",
      "ville": "Fès",
      "type_contrat": "Permanent",
      "experience_requise": "Senior (7+ ans)",
      "salaire_brut": null,
      "niveau_etudes": "Bac+5",
      "secteur": "Banque",
      "date_publication": "2024-07-22",
      "date_expiration": "2024-08-21",
      "nb_postes": 1,
      "teletravail": "télétravail",
      "langue_requise": [
        "Français",
        "Anglais"
      ]
    },
    {
      "id_offre": "RK-2024-01546",
      "source": "rekrute",
      "titre_poste": "Développeur BI",
      "description": "Nous recherchons un profil qualifie. Connaissances exigees : GCP, BigQuery, Airflow. Travail en equipe Agile.",
      "competences_brut": "AWS • Python • Docker",
      "entreprise": "TangerMedTech",
      "ville": "casa",
      "type_contrat": "Freelance",
      "experience_requise": "Débutant accepté",
      "salaire_brut": "8000-12000 dh",
      "niveau_etudes": "Bac+3",
      "secteur": "Banque",
      "date_publication": "2024-07-30",
      "date_expiration": "2024-08-29",
      "nb_postes": 2,
      "teletravail": "télétravail",
      "langue_requise": [
        "Français",
        "Anglais"
      ]
    },
    {
      "id_offre": "RK-2024-01572",
      "source": "rekrute",
      "titre_poste": "Data Scientist",
      "description": "Nous recherchons un profil qualifie. Connaissances exigees : AWS • Python • Docker. Travail en equipe Agile.",
      "competences_brut": "GCP, BigQuery, Airflow",
      "entreprise": "BankAlMaghrib",
      "ville": "Casablanca",
      "type_contrat": "CDI",
      "experience_requise": null,
      "salaire_brut": "Confidentiel",
      "niveau_etudes": "Bac+3",
      "secteur": "Banque",
      "date_publication": "2024-07-23",
      "date_expiration": "2024-08-22",
      "nb_postes": 2,
      "teletravail": "Remote",
      "langue_requise": [
        "Français",
        "Anglais"
      ]
    },
    {
      "id_offre": "RK-2024-01611",
      "source": "rekrute",
      "titre_poste": "Data Eng.",
      "description": "Nous recherchons un profil qualifie. Connaissances exigees : React, Node.js, PostgreSQL. Travail en equipe Agile.",
      "competences_brut": "AWS • Python • Docker",
      "entreprise": "DataWize",
      "ville": "Tanger",
      "type_contrat": "Contrat à durée indéterminée",
      "experience_requise": null,
      "salaire_brut": "8000-12000 dh",
      "niveau_etudes": "Ingénieur",
      "secteur": "Informatique / Télécom",
      "date_publication": "2024-07-27",
      "date_expiration": "2024-08-26",
      "nb_postes": 3,
      "teletravail": "Présentiel",
      "langue_requise": [
        "Français",
        "Anglais"
      ]
    },
    {
      "id_offre": "RK-2024-01643",
      "source": "rekrute",
      "titre_poste": "SysAdmin",
      "description": "Nous recherchons un profil qualifie. Connaissances exigees : AWS • Python • Docker. Travail en equipe Agile.",
      "competences_brut": "Python / SQL / Spark",
      "entreprise": "BankAlMaghrib",
      "ville": "casa",
      "type_contrat": "cdi",
      "experience_requise": "3-5 ans",
      "salaire_brut": "2000 EUR",
      "niveau_etudes": "Ingénieur",
      "secteur": "Informatique / Télécom",
      "date_publication": "2024-07-03",
      "date_expiration": "2024-08-02",
      "nb_postes": 1,
      "teletravail": "télétravail",
      "langue_requise": [
        "Français",
        "Anglais"
      ]
    },
    {
      "id_offre": "RK-2024-01678",
      "source": "rekrute",
      "titre_poste": "Data Scientist",
      "description": "Nous recherchons un profil qualifie. Connaissances exigees : AWS • Python • Docker. Travail en equipe Agile.",
      "competences_brut": "Java, Spring, Angular",
      "entreprise": "TangerMedTech",
      "ville": "Fès",
      "type_contrat": "cdi",
      "experience_requise": null,
      "salaire_brut": "15K-20K",
      "niveau_etudes": "Bac+3",
      "secteur": "Informatique / Télécom",
      "date_publication": "2024-07-18",
      "date_expiration": "2024-08-17",
      "nb_postes": 1,
      "teletravail": "télétravail",
      "langue_requise": [
        "Français",
        "Anglais"
      ]
    },
    {
      "id_offre": "RK-2024-01708",
      "source": "rekrute",
      "titre_poste": "Développeur BI",
      "description": "Nous recherchons un profil qualifie. Connaissances exigees : React, Node.js, PostgreSQL. Travail en equipe Agile.",
      "competences_brut": "Java, Spring, Angular",
      "entreprise": "Inwi",
      "ville": "CASABLANCA",
      "type_contrat": "Freelance",
      "experience_requise": "3 à 5 ans",
      "salaire_brut": "Confidentiel",
      "niveau_etudes": "Bac+5",
      "secteur": "Banque",
      "date_publication": "2024-07-29",
      "date_expiration": "2024-08-28",
      "nb_postes": 3,
      "teletravail": "Présentiel",
      "langue_requise": [
        "Français",
        "Anglais"
      ]
    },
    {
      "id_offre": "RK-2024-01746",
      "source": "rekrute",
      "titre_poste": "Data Engineer Junior",
      "description": "Nous recherchons un profil qualifie. Connaissances exigees : Java, Spring, Angular. Travail en equipe Agile.",
      "competences_brut": "Python / SQL / Spark",
      "entreprise": "BankAlMaghrib",
      "ville": "Marrakech",
      "type_contrat": "CDI",
      "experience_requise": "3-5 ans",
      "salaire_brut": "15000-20000 MAD",
      "niveau_etudes": "Bac+3",
      "secteur": "Conseil",
      "date_publication": "2024-07-20",
      "date_expiration": "2024-08-19",
      "nb_postes": 1,
      "teletravail": "Remote",
      "langue_requise": [
        "Français",
        "Anglais"
      ]
    },
    {
      "id_offre": "RK-2024-01820",
      "source": "rekrute",
      "titre_poste": "Data Engineer Junior",
      "description": "Nous recherchons un profil qualifie. Connaissances exigees : Python / SQL / Spark. Travail en equipe Agile.",
      "competences_brut": "Java, Spring, Angular",
      "entreprise": "Inwi",
      "ville": "CASABLANCA",
      "type_contrat": "Freelance",
      "experience_requise": "3-5 ans",
      "salaire_brut": null,
      "niveau_etudes": "Bac+3",
      "secteur": "Banque",
      "date_publication": "2024-07-03",
      "date_expiration": "2024-08-02",
      "nb_postes": 3,
      "teletravail": "Présentiel",
      "langue_requise": [
        "Français",
        "Anglais"
      ]
    },
    {
      "id_offre": "RK-2024-01874",
      "source": "rekrute",
      "titre_poste": "Data Eng.",
      "description": "Nous recherchons un profil qualifie. Connaissances exigees : Java, Spring, Angular. Travail en equipe Agile.",
      "competences_brut": "GCP, BigQuery, Airflow",
      "entreprise": "TangerMedTech",
      "ville": "Casablanca",
      "type_contrat": "cdi",
      "experience_requise": "Débutant accepté",
      "salaire_brut": "8000-12000 dh",
      "niveau_etudes": "Ingénieur",
      "secteur": "Informatique / Télécom",
      "date_publication": "2024-07-08",
      "date_expiration": "2024-08-07",
      "nb_postes": 2,
      "teletravail": "Remote",
      "langue_requise": [
        "Français",
        "Anglais"
      ]
    },
    {
      "id_offre": "RK-2024-01942",
      "source": "rekrute",
      "titre_poste": "Data Engineer Junior",
      "description": "Nous recherchons un profil qualifie. Connaissances exigees : Java, Spring, Angular. Travail en equipe Agile.",
      "competences_brut": "AWS • Python • Docker",
      "entreprise": "Inwi",
      "ville": "casa",
      "type_contrat": "CDI",
      "experience_requise": "Débutant accepté",
      "salaire_brut": null,
      "niveau_etudes": "Ingénieur",
      "secteur": "Banque",
      "date_publication": "2024-07-02",
      "date_expiration": "2024-08-01",
      "nb_postes": 1,
      "teletravail": "Présentiel",
      "langue_requise": [
        "Français",
        "Anglais"
      ]
    },
    {
      "id_offre": "RK-2024-01977",
      "source": "rekrute",
      "titre_poste": "Data Engineer Junior",
      "description": "Nous recherchons un profil qualifie. Connaissances exigees : Power BI, SQL, Excel. Travail en equipe Agile.",
      "competences_brut": "React, Node.js, PostgreSQL",
      "entreprise": "BankAlMaghrib",
      "ville": "Rabat",
      "type_contrat": "Contrat à durée indéterminée",
      "experience_requise": null,
      "salaire_brut": "Selon profil",
      "niveau_etudes": "Bac+5",
      "secteur": "Conseil",
      "date_publication": "2024-07-10",
      "date_expiration": "2024-08-09",
      "nb_postes": 3,
      "teletravail": "télétravail",
      "langue_requise": [
        "Français",
        "Anglais"
      ]
    },
    {
      "id_offre": "RK-2024-01983",
      "source": "rekrute",
      "titre_poste": "Développeur BI",
      "description": "Nous recherchons un profil qualifie. Connaissances exigees : Java, Spring, Angular. Travail en equipe Agile.",
      "competences_brut": "AWS • Python • Docker",
      "entreprise": "BankAlMaghrib",
      "ville": "Rabat",
      "type_contrat": "cdi",
      "experience_requise": "Senior (7+ ans)",
      "salaire_brut": "2000 EUR",
      "niveau_etudes": "Bac+3",
      "secteur": "Informatique / Télécom",
      "date_publication": "2024-07-12",
      "date_expiration": "2024-08-11",
      "nb_postes": 1,
      "teletravail": "Hybride",
      "langue_requise": [
        "Français",
        "Anglais"
      ]
    },
    {
      "id_offre": "RK-2024-02057",
      "source": "rekrute",
      "titre_poste": "SysAdmin",
      "description": "Nous recherchons un profil qualifie. Connaissances exigees : Power BI, SQL, Excel. Travail en equipe Agile.",
      "competences_brut": "Java, Spring, Angular",
      "entreprise": "BankAlMaghrib",
      "ville": "CASABLANCA",
      "type_contrat": "cdi",
      "experience_requise": "3-5 ans",
      "salaire_brut": "8000-12000 dh",
      "niveau_etudes": "Ingénieur",
      "secteur": "Informatique / Télécom",
      "date_publication": "2024-07-20",
      "date_expiration": "2024-08-19",
      "nb_postes": 1,
      "teletravail": "Hybride",
      "langue_requise": [
        "Français",
        "Anglais"
      ]
    },
    {
      "id_offre": "RK-2024-02059",
      "source": "rekrute",
      "titre_poste": "Dev Data",
      "description": "Nous recherchons un profil qualifie. Connaissances exigees : Java, Spring, Angular. Travail en equipe Agile.",
      "competences_brut": "React, Node.js, PostgreSQL",
      "entreprise": "TangerMedTech",
      "ville": "Casablanca",
      "type_contrat": "Freelance",
      "experience_requise": "min 3 ans",
      "salaire_brut": "15K-20K",
      "niveau_etudes": "Bac+5",
      "secteur": "Conseil",
      "date_publication": "2024-07-03",
      "date_expiration": "2024-08-02",
      "nb_postes": 3,
      "teletravail": "Remote",
      "langue_requise": [
        "Français",
        "Anglais"
      ]
    },
    {
      "id_offre": "RK-2024-02199",
      "source": "rekrute",
      "titre_poste": "Ingénieur Big Data",
      "description": "Nous recherchons un profil qualifie. Connaissances exigees : Java, Spring, Angular. Travail en equipe Agile.",
      "competences_brut": "React, Node.js, PostgreSQL",
      "entreprise": "BankAlMaghrib",
      "ville": "casa",
      "type_contrat": "Contrat à durée indéterminée",
      "experience_requise": "min 3 ans",
      "salaire_brut": null,
      "niveau_etudes": "Ingénieur",
      "secteur": "Informatique / Télécom",
      "date_publication": "2024-07-18",
      "date_expiration": "2024-08-17",
      "nb_postes": 2,
      "teletravail": "télétravail",
      "langue_requise": [
        "Français",
        "Anglais"
      ]
    },
    {
      "id_offre": "RK-2024-02215",
      "source": "rekrute",
      "titre_poste": "SysAdmin",
      "description": "Nous recherchons un profil qualifie. Connaissances exigees : AWS • Python • Docker. Travail en equipe Agile.",
      "competences_brut": "Java, Spring, Angular",
      "entreprise": "DataWize",
      "ville": "Tanger",
      "type_contrat": "Contrat à durée indéterminée",
      "experience_requise": "Débutant accepté",
      "salaire_brut": "15K-20K",
      "niveau_etudes": "Bac+5",
      "secteur": "Conseil",
      "date_publication": "2024-07-02",
      "date_expiration": "2024-08-01",
      "nb_postes": 3,
      "teletravail": "Présentiel",
      "langue_requise": [
        "Français",
        "Anglais"
      ]
    },
    {
      "id_offre": "RK-2024-02216",
      "source": "rekrute",
      "titre_poste": "Ingénieur Big Data",
      "description": "Nous recherchons un profil qualifie. Connaissances exigees : React, Node.js, PostgreSQL. Travail en equipe Agile.",
      "competences_brut": "Java, Spring, Angular",
      "entreprise": "DataWize",
      "ville": "Marrakech",
      "type_contrat": "CDI",
      "experience_requise": "3-5 ans",
      "salaire_brut": "2000 EUR",
      "niveau_etudes": "Bac+5",
      "secteur": "Informatique / Télécom",
      "date_publication": "2024-07-02",
      "date_expiration": "2024-08-01",
      "nb_postes": 1,
      "teletravail": "Remote",
      "langue_requise": [
        "Français",
        "Anglais"
      ]
    },
    {
      "id_offre": "RK-2024-02231",
      "source": "rekrute",
      "titre_poste": "Data Eng.",
      "description": "Nous recherchons un profil qualifie. Connaissances exigees : Python / SQL / Spark. Travail en equipe Agile.",
      "competences_brut": "Power BI, SQL, Excel",
      "entreprise": "TechMaroc SARL",
      "ville": "Fès",
      "type_contrat": "Permanent",
      "experience_requise": "3 à 5 ans",
      "salaire_brut": null,
      "niveau_etudes": "Ingénieur",
      "secteur": "Banque",
      "date_publication": "2024-07-10",
      "date_expiration": "2024-08-09",
      "nb_postes": 2,
      "teletravail": "télétravail",
      "langue_requise": [
        "Français",
        "Anglais"
      ]
    },
    {
      "id_offre": "RK-2024-02245",
      "source": "rekrute",
      "titre_poste": "Data Eng.",
      "description": "Nous recherchons un profil qualifie. Connaissances exigees : GCP, BigQuery, Airflow. Travail en equipe Agile.",
      "competences_brut": "Power BI, SQL, Excel",
      "entreprise": "Inwi",
      "ville": "casa",
      "type_contrat": "Contrat à durée indéterminée",
      "experience_requise": null,
      "salaire_brut": "2000 EUR",
      "niveau_etudes": "Bac+5",
      "secteur": "Conseil",
      "date_publication": "2024-07-27",
      "date_expiration": "2024-08-26",
      "nb_postes": 1,
      "teletravail": "télétravail",
      "langue_requise": [
        "Français",
        "Anglais"
      ]
    },
    {
      "id_offre": "RK-2024-02303",
      "source": "rekrute",
      "titre_poste": "Ingénieur Big Data",
      "description": "Nous recherchons un profil qualifie. Connaissances exigees : Power BI, SQL, Excel. Travail en equipe Agile.",
      "competences_brut": "Power BI, SQL, Excel",
      "entreprise": "TechMaroc SARL",
      "ville": "casa",
      "type_contrat": "cdi",
      "experience_requise": null,
      "salaire_brut": "Confidentiel",
      "niveau_etudes": "Bac+5",
      "secteur": "Conseil",
      "date_publication": "2024-07-03",
      "date_expiration": "2024-08-02",
      "nb_postes": 3,
      "teletravail": "Hybride",
      "langue_requise": [
        "Français",
        "Anglais"
      ]
    },
    {
      "id_offre": "RK-2024-02444",
      "source": "rekrute",
      "titre_poste": "Développeur Full Stack React/Node.js",
      "description": "Nous recherchons un profil qualifie. Connaissances exigees : GCP, BigQuery, Airflow. Travail en equipe Agile.",
      "competences_brut": "Java, Spring, Angular",
      "entreprise": "Inwi",
      "ville": "CASABLANCA",
      "type_contrat": "Contrat à durée indéterminée",
      "experience_requise": "Débutant accepté",
      "salaire_brut": "15K-20K",
      "niveau_etudes": "Ingénieur",
      "secteur": "Informatique / Télécom",
      "date_publication": "2024-07-05",
      "date_expiration": "2024-08-04",
      "nb_postes": 3,
      "teletravail": "télétravail",
      "langue_requise": [
        "Français",
        "Anglais"
      ]
    },
    {
      "id_offre": "RK-2024-02572",
      "source": "rekrute",
      "titre_poste": "Data Engineer Junior",
      "description": "Nous recherchons un profil qualifie. Connaissances exigees : GCP, BigQuery, Airflow. Travail en equipe Agile.",
      "competences_brut": "Python / SQL / Spark",
      "entreprise": "TangerMedTech",
      "ville": "Casablanca",
      "type_contrat": "Permanent",
      "experience_requise": "Débutant accepté",
      "salaire_brut": null,
      "niveau_etudes": "Bac+5",
      "secteur": "Banque",
      "date_publication": "2024-07-03",
      "date_expiration": "2024-08-02",
      "nb_postes": 3,
      "teletravail": "Présentiel",
      "langue_requise": [
        "Français",
        "Anglais"
      ]
    },
    {
      "id_offre": "RK-2024-02629",
      "source": "rekrute",
      "titre_poste": "Développeur BI",
      "description": "Nous recherchons un profil qualifie. Connaissances exigees : AWS • Python • Docker. Travail en equipe Agile.",
      "competences_brut": "Java, Spring, Angular",
      "entreprise": "TangerMedTech",
      "ville": "Marrakech",
      "type_contrat": "Freelance",
      "experience_requise": "3-5 ans",
      "salaire_brut": "Selon profil",
      "niveau_etudes": "Bac+5",
      "secteur": "Banque",
      "date_publication": "2024-07-02",
      "date_expiration": "2024-08-01",
      "nb_postes": 1,
      "teletravail": "télétravail",
      "langue_requise": [
        "Français",
        "Anglais"
      ]
    },
    {
      "id_offre": "RK-2024-02634",
      "source": "rekrute",
      "titre_poste": "Data Scientist",
      "description": "Nous recherchons un profil qualifie. Connaissances exigees : React, Node.js, PostgreSQL. Travail en equipe Agile.",
      "competences_brut": "AWS • Python • Docker",
      "entreprise": "Inwi",
      "ville": "Marrakech",
      "type_contrat": "Permanent",
      "experience_requise": "Senior (7+ ans)",
      "salaire_brut": "2000 EUR",
      "niveau_etudes": "Bac+5",
      "secteur": "Banque",
      "date_publication": "2024-07-13",
      "date_expiration": "2024-08-12",
      "nb_postes": 1,
      "teletravail": "télétravail",
      "langue_requise": [
        "Français",
        "Anglais"
      ]
    },
    {
      "id_offre": "RK-2024-02714",
      "source": "rekrute",
      "titre_poste": "Data Engineer Junior",
      "description": "Nous recherchons un profil qualifie. Connaissances exigees : AWS • Python • Docker. Travail en equipe Agile.",
      "competences_brut": "Java, Spring, Angular",
      "entreprise": "DataWize",
      "ville": "Fès",
      "type_contrat": "Freelance",
      "experience_requise": "min 3 ans",
      "salaire_brut": "8000-12000 dh",
      "niveau_etudes": "Ingénieur",
      "secteur": "Informatique / Télécom",
      "date_publication": "2024-07-23",
      "date_expiration": "2024-08-22",
      "nb_postes": 3,
      "teletravail": "télétravail",
      "langue_requise": [
        "Français",
        "Anglais"
      ]
    },
    {
      "id_offre": "RK-2024-02767",
      "source": "rekrute",
      "titre_poste": "Développeur BI",
      "description": "Nous recherchons un profil qualifie. Connaissances exigees : Java, Spring, Angular. Travail en equipe Agile.",
      "competences_brut": "Power BI, SQL, Excel",
      "entreprise": "TechMaroc SARL",
      "ville": "casa",
      "type_contrat": "cdi",
      "experience_requise": "min 3 ans",
      "salaire_brut": "Confidentiel",
      "niveau_etudes": "Bac+5",
      "secteur": "Conseil",
      "date_publication": "2024-07-14",
      "date_expiration": "2024-08-13",
      "nb_postes": 2,
      "teletravail": "Remote",
      "langue_requise": [
        "Français",
        "Anglais"
      ]
    },
    {
      "id_offre": "RK-2024-02781",
      "source": "rekrute",
      "titre_poste": "DevOps",
      "description": "Nous recherchons un profil qualifie. Connaissances exigees : Java, Spring, Angular. Travail en equipe Agile.",
      "competences_brut": "Python / SQL / Spark",
      "entreprise": "DataWize",
      "ville": "Rabat",
      "type_contrat": "Freelance",
      "experience_requise": "min 3 ans",
      "salaire_brut": "Selon profil",
      "niveau_etudes": "Bac+3",
      "secteur": "Informatique / Télécom",
      "date_publication": "2024-07-03",
      "date_expiration": "2024-08-02",
      "nb_postes": 2,
      "teletravail": "télétravail",
      "langue_requise": [
        "Français",
        "Anglais"
      ]
    },
    {
      "id_offre": "RK-2024-02793",
      "source": "rekrute",
      "titre_poste": "Data Engineer Junior",
      "description": "Nous recherchons un profil qualifie. Connaissances exigees : Python / SQL / Spark. Travail en equipe Agile.",
      "competences_brut": "AWS • Python • Docker",
      "entreprise": "Inwi",
      "ville": "casa",
      "type_contrat": "Permanent",
      "experience_requise": "3-5 ans",
      "salaire_brut": "2000 EUR",
      "niveau_etudes": "Ingénieur",
      "secteur": "Conseil",
      "date_publication": "2024-07-25",
      "date_expiration": "2024-08-24",
      "nb_postes": 1,
      "teletravail": "télétravail",
      "langue_requise": [
        "Français",
        "Anglais"
      ]
    },
    {
      "id_offre": "RK-2024-03010",
      "source": "rekrute",
      "titre_poste": "Développeur BI",
      "description": "Nous recherchons un profil qualifie. Connaissances exigees : Python / SQL / Spark. Travail en equipe Agile.",
      "competences_brut": "React, Node.js, PostgreSQL",
      "entreprise": "TechMaroc SARL",
      "ville": "CASABLANCA",
      "type_contrat": "Permanent",
      "experience_requise": "Débutant accepté",
      "salaire_brut": null,
      "niveau_etudes": "Bac+3",
      "secteur": "Conseil",
      "date_publication": "2024-07-10",
      "date_expiration": "2024-08-09",
      "nb_postes": 1,
      "teletravail": "Présentiel",
      "langue_requise": [
        "Français",
        "Anglais"
      ]
    },
    {
      "id_offre": "RK-2024-03199",
      "source": "rekrute",
      "titre_poste": "Développeur BI",
      "description": "Nous recherchons un profil qualifie. Connaissances exigees : AWS • Python • Docker. Travail en equipe Agile.",
      "competences_brut": "Java, Spring, Angular",
      "entreprise": "TechMaroc SARL",
      "ville": "Casablanca",
      "type_contrat": "Contrat à durée indéterminée",
      "experience_requise": null,
      "salaire_brut": "8000-12000 dh",
      "niveau_etudes": "Bac+3",
      "secteur": "Conseil",
      "date_publication": "2024-07-10",
      "date_expiration": "2024-08-09",
      "nb_postes": 3,
      "teletravail": "Présentiel",
      "langue_requise": [
        "Français",
        "Anglais"
      ]
    },
    {
      "id_offre": "RK-2024-03201",
      "source": "rekrute",
      "titre_poste": "Développeur Full Stack React/Node.js",
      "description": "Nous recherchons un profil qualifie. Connaissances exigees : Python / SQL / Spark. Travail en equipe Agile.",
      "competences_brut": "GCP, BigQuery, Airflow",
      "entreprise": "Inwi",
      "ville": "Marrakech",
      "type_contrat": "Permanent",
      "experience_requise": null,
      "salaire_brut": "15000-20000 MAD",
      "niveau_etudes": "Bac+5",
      "secteur": "Banque",
      "date_publication": "2024-07-08",
      "date_expiration": "2024-08-07",
      "nb_postes": 1,
      "teletravail": "Hybride",
      "langue_requise": [
        "Français",
        "Anglais"
      ]
    },
    {
      "id_offre": "RK-2024-03229",
      "source": "rekrute",
      "titre_poste": "DevOps",
      "description": "Nous recherchons un profil qualifie. Connaissances exigees : GCP, BigQuery, Airflow. Travail en equipe Agile.",
      "competences_brut": "GCP, BigQuery, Airflow",
      "entreprise": "BankAlMaghrib",
      "ville": "Casablanca",
      "type_contrat": "Contrat à durée indéterminée",
      "experience_requise": "3 à 5 ans",
      "salaire_brut": "2000 EUR",
      "niveau_etudes": "Bac+3",
      "secteur": "Informatique / Télécom",
      "date_publication": "2024-07-22",
      "date_expiration": "2024-08-21",
      "nb_postes": 3,
      "teletravail": "télétravail",
      "langue_requise": [
        "Français",
        "Anglais"
      ]
    },
    {
      "id_offre": "RK-2024-03333",
      "source": "rekrute",
      "titre_poste": "Data Engineer Junior",
      "description": "Nous recherchons un profil qualifie. Connaissances exigees : Python / SQL / Spark. Travail en equipe Agile.",
      "competences_brut": "AWS • Python • Docker",
      "entreprise": "TangerMedTech",
      "ville": "Casablanca",
      "type_contrat": "Permanent",
      "experience_requise": "min 3 ans",
      "salaire_brut": "Confidentiel",
      "niveau_etudes": "Ingénieur",
      "secteur": "Conseil",
      "date_publication": "2024-07-14",
      "date_expiration": "2024-08-13",
      "nb_postes": 2,
      "teletravail": "Remote",
      "langue_requise": [
        "Français",
        "Anglais"
      ]
    },
    {
      "id_offre": "RK-2024-03340",
      "source": "rekrute",
      "titre_poste": "Développeur Full Stack React/Node.js",
      "description": "Nous recherchons un profil qualifie. Connaissances exigees : Java, Spring, Angular. Travail en equipe Agile.",
      "competences_brut": "Power BI, SQL, Excel",
      "entreprise": "TangerMedTech",
      "ville": "Casablanca",
      "type_contrat": "CDI",
      "experience_requise": null,
      "salaire_brut": "8000-12000 dh",
      "niveau_etudes": "Ingénieur",
      "secteur": "Conseil",
      "date_publication": "2024-07-06",
      "date_expiration": "2024-08-05",
      "nb_postes": 1,
      "teletravail": "Hybride",
      "langue_requise": [
        "Français",
        "Anglais"
      ]
    },
    {
      "id_offre": "RK-2024-03385",
      "source": "rekrute",
      "titre_poste": "Dev Data",
      "description": "Nous recherchons un profil qualifie. Connaissances exigees : Java, Spring, Angular. Travail en equipe Agile.",
      "competences_brut": "Java, Spring, Angular",
      "entreprise": "DataWize",
      "ville": "casa",
      "type_contrat": "Contrat à durée indéterminée",
      "experience_requise": "Débutant accepté",
      "salaire_brut": "Selon profil",
      "niveau_etudes": "Bac+5",
      "secteur": "Banque",
      "date_publication": "2024-07-18",
      "date_expiration": "2024-08-17",
      "nb_postes": 1,
      "teletravail": "Présentiel",
      "langue_requise": [
        "Français",
        "Anglais"
      ]
    },
    {
      "id_offre": "RK-2024-03394",
      "source": "rekrute",
      "titre_poste": "DevOps",
      "description": "Nous recherchons un profil qualifie. Connaissances exigees : Java, Spring, Angular. Travail en equipe Agile.",
      "competences_brut": "Java, Spring, Angular",
      "entreprise": "TangerMedTech",
      "ville": "Casablanca",
      "type_contrat": "cdi",
      "experience_requise": "3-5 ans",
      "salaire_brut": "2000 EUR",
      "niveau_etudes": "Bac+3",
      "secteur": "Banque",
      "date_publication": "2024-07-27",
      "date_expiration": "2024-08-26",
      "nb_postes": 2,
      "teletravail": "Remote",
      "langue_requise": [
        "Français",
        "Anglais"
      ]
    },
    {
      "id_offre": "RK-2024-03455",
      "source": "rekrute",
      "titre_poste": "Data Scientist",
      "description": "Nous recherchons un profil qualifie. Connaissances exigees : React, Node.js, PostgreSQL. Travail en equipe Agile.",
      "competences_brut": "React, Node.js, PostgreSQL",
      "entreprise": "TechMaroc SARL",
      "ville": "Fès",
      "type_contrat": "Contrat à durée indéterminée",
      "experience_requise": "Débutant accepté",
      "salaire_brut": "8000-12000 dh",
      "niveau_etudes": "Ingénieur",
      "secteur": "Banque",
      "date_publication": "2024-07-29",
      "date_expiration": "2024-08-28",
      "nb_postes": 1,
      "teletravail": "Présentiel",
      "langue_requise": [
        "Français",
        "Anglais"
      ]
    },
    {
      "id_offre": "RK-2024-03465",
      "source": "rekrute",
      "titre_poste": "Data Eng.",
      "description": "Nous recherchons un profil qualifie. Connaissances exigees : Power BI, SQL, Excel. Travail en equipe Agile.",
      "competences_brut": "AWS • Python • Docker",
      "entreprise": "BankAlMaghrib",
      "ville": "Tanger",
      "type_contrat": "CDI",
      "experience_requise": "Débutant accepté",
      "salaire_brut": "2000 EUR",
      "niveau_etudes": "Bac+5",
      "secteur": "Banque",
      "date_publication": "2024-07-27",
      "date_expiration": "2024-08-26",
      "nb_postes": 3,
      "teletravail": "Remote",
      "langue_requise": [
        "Français",
        "Anglais"
      ]
    },
    {
      "id_offre": "RK-2024-03481",
      "source": "rekrute",
      "titre_poste": "Dev Data",
      "description": "Nous recherchons un profil qualifie. Connaissances exigees : Java, Spring, Angular. Travail en equipe Agile.",
      "competences_brut": "Java, Spring, Angular",
      "entreprise": "TechMaroc SARL",
      "ville": "casa",
      "type_contrat": "Permanent",
      "experience_requise": null,
      "salaire_brut": "2000 EUR",
      "niveau_etudes": "Bac+3",
      "secteur": "Informatique / Télécom",
      "date_publication": "2024-07-23",
      "date_expiration": "2024-08-22",
      "nb_postes": 2,
      "teletravail": "Présentiel",
      "langue_requise": [
        "Français",
        "Anglais"
      ]
    },
    {
      "id_offre": "RK-2024-03520",
      "source": "rekrute",
      "titre_poste": "Data Scientist",
      "description": "Nous recherchons un profil qualifie. Connaissances exigees : AWS • Python • Docker. Travail en equipe Agile.",
      "competences_brut": "Python / SQL / Spark",
      "entreprise": "BankAlMaghrib",
      "ville": "casa",
      "type_contrat": "Freelance",
      "experience_requise": "Débutant accepté",
      "salaire_brut": null,
      "niveau_etudes": "Ingénieur",
      "secteur": "Conseil",
      "date_publication": "2024-07-13",
      "date_expiration": "2024-08-12",
      "nb_postes": 2,
      "teletravail": "Hybride",
      "langue_requise": [
        "Français",
        "Anglais"
      ]
    },
    {
      "id_offre": "RK-2024-03572",
      "source": "rekrute",
      "titre_poste": "Ingénieur Big Data",
      "description": "Nous recherchons un profil qualifie. Connaissances exigees : GCP, BigQuery, Airflow. Travail en equipe Agile.",
      "competences_brut": "Python / SQL / Spark",
      "entreprise": "BankAlMaghrib",
      "ville": "Marrakech",
      "type_contrat": "cdi",
      "experience_requise": "3-5 ans",
      "salaire_brut": "15000-20000 MAD",
      "niveau_etudes": "Ingénieur",
      "secteur": "Banque",
      "date_publication": "2024-07-16",
      "date_expiration": "2024-08-15",
      "nb_postes": 2,
      "teletravail": "Hybride",
      "langue_requise": [
        "Français",
        "Anglais"
      ]
    },
    {
      "id_offre": "RK-2024-03667",
      "source": "rekrute",
      "titre_poste": "Data Scientist",
      "description": "Nous recherchons un profil qualifie. Connaissances exigees : Python / SQL / Spark. Travail en equipe Agile.",
      "competences_brut": "React, Node.js, PostgreSQL",
      "entreprise": "BankAlMaghrib",
      "ville": "casa",
      "type_contrat": "Contrat à durée indéterminée",
      "experience_requise": "Débutant accepté",
      "salaire_brut": null,
      "niveau_etudes": "Ingénieur",
      "secteur": "Banque",
      "date_publication": "2024-07-07",
      "date_expiration": "2024-08-06",
      "nb_postes": 3,
      "teletravail": "Hybride",
      "langue_requise": [
        "Français",
        "Anglais"
      ]
    },
    {
      "id_offre": "RK-2024-03679",
      "source": "rekrute",
      "titre_poste": "Développeur BI",
      "description": "Nous recherchons un profil qualifie. Connaissances exigees : Java, Spring, Angular. Travail en equipe Agile.",
      "competences_brut": "Power BI, SQL, Excel",
      "entreprise": "DataWize",
      "ville": "Casablanca",
      "type_contrat": "Permanent",
      "experience_requise": "Senior (7+ ans)",
      "salaire_brut": "2000 EUR",
      "niveau_etudes": "Ingénieur",
      "secteur": "Informatique / Télécom",
      "date_publication": "2024-07-26",
      "date_expiration": "2024-08-25",
      "nb_postes": 2,
      "teletravail": "télétravail",
      "langue_requise": [
        "Français",
        "Anglais"
      ]
    },
    {
      "id_offre": "RK-2024-03732",
      "source": "rekrute",
      "titre_poste": "SysAdmin",
      "description": "Nous recherchons un profil qualifie. Connaissances exigees : AWS • Python • Docker. Travail en equipe Agile.",
      "competences_brut": "Java, Spring, Angular",
      "entreprise": "DataWize",
      "ville": "Fès",
      "type_contrat": "CDI",
      "experience_requise": "min 3 ans",
      "salaire_brut": "Selon profil",
      "niveau_etudes": "Bac+5",
      "secteur": "Banque",
      "date_publication": "2024-07-16",
      "date_expiration": "2024-08-15",
      "nb_postes": 3,
      "teletravail": "télétravail",
      "langue_requise": [
        "Français",
        "Anglais"
      ]
    },
    {
      "id_offre": "RK-2024-03747",
      "source": "rekrute",
      "titre_poste": "Dev Data",
      "description": "Nous recherchons un profil qualifie. Connaissances exigees : AWS • Python • Docker. Travail en equipe Agile.",
      "competences_brut": "Java, Spring, Angular",
      "entreprise": "TangerMedTech",
      "ville": "Fès",
      "type_contrat": "Freelance",
      "experience_requise": "Senior (7+ ans)",
      "salaire_brut": "Confidentiel",
      "niveau_etudes": "Bac+5",
      "secteur": "Informatique / Télécom",
      "date_publication": "2024-07-26",
      "date_expiration": "2024-08-25",
      "nb_postes": 3,
      "teletravail": "télétravail",
      "langue_requise": [
        "Français",
        "Anglais"
      ]
    },
    {
      "id_offre": "RK-2024-03754",
      "source": "rekrute",
      "titre_poste": "Développeur Full Stack React/Node.js",
      "description": "Nous recherchons un profil qualifie. Connaissances exigees : Python / SQL / Spark. Travail en equipe Agile.",
      "competences_brut": "Python / SQL / Spark",
      "entreprise": "DataWize",
      "ville": "Casablanca",
      "type_contrat": "Freelance",
      "experience_requise": "Senior (7+ ans)",
      "salaire_brut": "15K-20K",
      "niveau_etudes": "Bac+3",
      "secteur": "Banque",
      "date_publication": "2024-07-08",
      "date_expiration": "2024-08-07",
      "nb_postes": 1,
      "teletravail": "Remote",
      "langue_requise": [
        "Français",
        "Anglais"
      ]
    },
    {
      "id_offre": "RK-2024-03778",
      "source": "rekrute",
      "titre_poste": "DevOps",
      "description": "Nous recherchons un profil qualifie. Connaissances exigees : GCP, BigQuery, Airflow. Travail en equipe Agile.",
      "competences_brut": "AWS • Python • Docker",
      "entreprise": "TangerMedTech",
      "ville": "Tanger",
      "type_contrat": "Permanent",
      "experience_requise": "3 à 5 ans",
      "salaire_brut": "Selon profil",
      "niveau_etudes": "Bac+3",
      "secteur": "Informatique / Télécom",
      "date_publication": "2024-07-04",
      "date_expiration": "2024-08-03",
      "nb_postes": 3,
      "teletravail": "Présentiel",
      "langue_requise": [
        "Français",
        "Anglais"
      ]
    },
    {
      "id_offre": "RK-2024-03787",
      "source": "rekrute",
      "titre_poste": "Data Scientist",
      "description": "Nous recherchons un profil qualifie. Connaissances exigees : Python / SQL / Spark. Travail en equipe Agile.",
      "competences_brut": "AWS • Python • Docker",
      "entreprise": "TangerMedTech",
      "ville": "CASABLANCA",
      "type_contrat": "cdi",
      "experience_requise": "Senior (7+ ans)",
      "salaire_brut": "Selon profil",
      "niveau_etudes": "Bac+5",
      "secteur": "Conseil",
      "date_publication": "2024-07-11",
      "date_expiration": "2024-08-10",
      "nb_postes": 3,
      "teletravail": "Hybride",
      "langue_requise": [
        "Français",
        "Anglais"
      ]
    },
    {
      "id_offre": "RK-2024-03800",
      "source": "rekrute",
      "titre_poste": "Ingénieur Big Data",
      "description": "Nous recherchons un profil qualifie. Connaissances exigees : React, Node.js, PostgreSQL. Travail en equipe Agile.",
      "competences_brut": "React, Node.js, PostgreSQL",
      "entreprise": "BankAlMaghrib",
      "ville": "Casablanca",
      "type_contrat": "CDI",
      "experience_requise": "min 3 ans",
      "salaire_brut": "Selon profil",
      "niveau_etudes": "Bac+5",
      "secteur": "Informatique / Télécom",
      "date_publication": "2024-07-02",
      "date_expiration": "2024-08-01",
      "nb_postes": 3,
      "teletravail": "télétravail",
      "langue_requise": [
        "Français",
        "Anglais"
      ]
    },
    {
      "id_offre": "RK-2024-03826",
      "source": "rekrute",
      "titre_poste": "Développeur BI",
      "description": "Nous recherchons un profil qualifie. Connaissances exigees : GCP, BigQuery, Airflow. Travail en equipe Agile.",
      "competences_brut": "Power BI, SQL, Excel",
      "entreprise": "TechMaroc SARL",
      "ville": "Casablanca",
      "type_contrat": "Freelance",
      "experience_requise": "3 à 5 ans",
      "salaire_brut": "15000-20000 MAD",
      "niveau_etudes": "Ingénieur",
      "secteur": "Informatique / Télécom",
      "date_publication": "2024-07-02",
      "date_expiration": "2024-08-01",
      "nb_postes": 1,
      "teletravail": "télétravail",
      "langue_requise": [
        "Français",
        "Anglais"
      ]
    },
    {
      "id_offre": "RK-2024-03851",
      "source": "rekrute",
      "titre_poste": "Développeur Full Stack React/Node.js",
      "description": "Nous recherchons un profil qualifie. Connaissances exigees : GCP, BigQuery, Airflow. Travail en equipe Agile.",
      "competences_brut": "AWS • Python • Docker",
      "entreprise": "DataWize",
      "ville": "Casablanca",
      "type_contrat": "Contrat à durée indéterminée",
      "experience_requise": null,
      "salaire_brut": null,
      "niveau_etudes": "Ingénieur",
      "secteur": "Banque",
      "date_publication": "2024-07-05",
      "date_expiration": "2024-08-04",
      "nb_postes": 1,
      "teletravail": "télétravail",
      "langue_requise": [
        "Français",
        "Anglais"
      ]
    },
    {
      "id_offre": "RK-2024-03903",
      "source": "rekrute",
      "titre_poste": "Développeur BI",
      "description": "Nous recherchons un profil qualifie. Connaissances exigees : React, Node.js, PostgreSQL. Travail en equipe Agile.",
      "competences_brut": "Python / SQL / Spark",
      "entreprise": "Inwi",
      "ville": "Rabat",
      "type_contrat": "CDI",
      "experience_requise": "Senior (7+ ans)",
      "salaire_brut": "8000-12000 dh",
      "niveau_etudes": "Bac+5",
      "secteur": "Banque",
      "date_publication": "2024-07-30",
      "date_expiration": "2024-08-29",
      "nb_postes": 1,
      "teletravail": "Hybride",
      "langue_requise": [
        "Français",
        "Anglais"
      ]
    },
    {
      "id_offre": "RK-2024-04141",
      "source": "rekrute",
      "titre_poste": "Développeur BI",
      "description": "Nous recherchons un profil qualifie. Connaissances exigees : GCP, BigQuery, Airflow. Travail en equipe Agile.",
      "competences_brut": "GCP, BigQuery, Airflow",
      "entreprise": "DataWize",
      "ville": "casa",
      "type_contrat": "Contrat à durée indéterminée",
      "experience_requise": "Débutant accepté",
      "salaire_brut": null,
      "niveau_etudes": "Ingénieur",
      "secteur": "Banque",
      "date_publication": "2024-07-30",
      "date_expiration": "2024-08-29",
      "nb_postes": 1,
      "teletravail": "Présentiel",
      "langue_requise": [
        "Français",
        "Anglais"
      ]
    },
    {
      "id_offre": "RK-2024-04373",
      "source": "rekrute",
      "titre_poste": "Data Eng.",
      "description": "Nous recherchons un profil qualifie. Connaissances exigees : Power BI, SQL, Excel. Travail en equipe Agile.",
      "competences_brut": "Java, Spring, Angular",
      "entreprise": "BankAlMaghrib",
      "ville": "Fès",
      "type_contrat": "CDI",
      "experience_requise": "Senior (7+ ans)",
      "salaire_brut": "Confidentiel",
      "niveau_etudes": "Bac+3",
      "secteur": "Banque",
      "date_publication": "2024-07-09",
      "date_expiration": "2024-08-08",
      "nb_postes": 2,
      "teletravail": "télétravail",
      "langue_requise": [
        "Français",
        "Anglais"
      ]
    },
    {
      "id_offre": "RK-2024-04415",
      "source": "rekrute",
      "titre_poste": "Data Eng.",
      "description": "Nous recherchons un profil qualifie. Connaissances exigees : Power BI, SQL, Excel. Travail en equipe Agile.",
      "competences_brut": "AWS • Python • Docker",
      "entreprise": "DataWize",
      "ville": "Tanger",
      "type_contrat": "Permanent",
      "experience_requise": "min 3 ans",
      "salaire_brut": "2000 EUR",
      "niveau_etudes": "Ingénieur",
      "secteur": "Banque",
      "date_publication": "2024-07-29",
      "date_expiration": "2024-08-28",
      "nb_postes": 2,
      "teletravail": "Hybride",
      "langue_requise": [
        "Français",
        "Anglais"
      ]
    },
    {
      "id_offre": "RK-2024-04444",
      "source": "rekrute",
      "titre_poste": "Data Scientist",
      "description": "Nous recherchons un profil qualifie. Connaissances exigees : Java, Spring, Angular. Travail en equipe Agile.",
      "competences_brut": "Power BI, SQL, Excel",
      "entreprise": "TangerMedTech",
      "ville": "Fès",
      "type_contrat": "Contrat à durée indéterminée",
      "experience_requise": "Senior (7+ ans)",
      "salaire_brut": "Selon profil",
      "niveau_etudes": "Bac+3",
      "secteur": "Conseil",
      "date_publication": "2024-07-07",
      "date_expiration": "2024-08-06",
      "nb_postes": 2,
      "teletravail": "Remote",
      "langue_requise": [
        "Français",
        "Anglais"
      ]
    },
    {
      "id_offre": "RK-2024-04449",
      "source": "rekrute",
      "titre_poste": "Développeur BI",
      "description": "Nous recherchons un profil qualifie. Connaissances exigees : Java, Spring, Angular. Travail en equipe Agile.",
      "competences_brut": "Python / SQL / Spark",
      "entreprise": "TangerMedTech",
      "ville": "Fès",
      "type_contrat": "Permanent",
      "experience_requise": "Débutant accepté",
      "salaire_brut": "15000-20000 MAD",
      "niveau_etudes": "Ingénieur",
      "secteur": "Conseil",
      "date_publication": "2024-07-06",
      "date_expiration": "2024-08-05",
      "nb_postes": 3,
      "teletravail": "télétravail",
      "langue_requise": [
        "Français",
        "Anglais"
      ]
    },
    {
      "id_offre": "RK-2024-04504",
      "source": "rekrute",
      "titre_poste": "Data Scientist",
      "description": "Nous recherchons un profil qualifie. Connaissances exigees : Power BI, SQL, Excel. Travail en equipe Agile.",
      "competences_brut": "React, Node.js, PostgreSQL",
      "entreprise": "TechMaroc SARL",
      "ville": "Rabat",
      "type_contrat": "Freelance",
      "experience_requise": "3 à 5 ans",
      "salaire_brut": null,
      "niveau_etudes": "Bac+5",
      "secteur": "Banque",
      "date_publication": "2024-07-10",
      "date_expiration": "2024-08-09",
      "nb_postes": 2,
      "teletravail": "Remote",
      "langue_requise": [
        "Français",
        "Anglais"
      ]
    },
    {
      "id_offre": "RK-2024-04615",
      "source": "rekrute",
      "titre_poste": "Data Scientist",
      "description": "Nous recherchons un profil qualifie. Connaissances exigees : Java, Spring, Angular. Travail en equipe Agile.",
      "competences_brut": "GCP, BigQuery, Airflow",
      "entreprise": "TechMaroc SARL",
      "ville": "Fès",
      "type_contrat": "Contrat à durée indéterminée",
      "experience_requise": "Senior (7+ ans)",
      "salaire_brut": "15000-20000 MAD",
      "niveau_etudes": "Ingénieur",
      "secteur": "Informatique / Télécom",
      "date_publication": "2024-07-31",
      "date_expiration": "2024-08-30",
      "nb_postes": 3,
      "teletravail": "Remote",
      "langue_requise": [
        "Français",
        "Anglais"
      ]
    },
    {
      "id_offre": "RK-2024-04664",
      "source": "rekrute",
      "titre_poste": "Dev Data",
      "description": "Nous recherchons un profil qualifie. Connaissances exigees : Power BI, SQL, Excel. Travail en equipe Agile.",
      "competences_brut": "GCP, BigQuery, Airflow",
      "entreprise": "DataWize",
      "ville": "Rabat",
      "type_contrat": "Permanent",
      "experience_requise": null,
      "salaire_brut": "15K-20K",
      "niveau_etudes": "Bac+3",
      "secteur": "Informatique / Télécom",
      "date_publication": "2024-07-21",
      "date_expiration": "2024-08-20",
      "nb_postes": 1,
      "teletravail": "Remote",
      "langue_requise": [
        "Français",
        "Anglais"
      ]
    },
    {
      "id_offre": "RK-2024-04666",
      "source": "rekrute",
      "titre_poste": "Data Scientist",
      "description": "Nous recherchons un profil qualifie. Connaissances exigees : Java, Spring, Angular. Travail en equipe Agile.",
      "competences_brut": "Power BI, SQL, Excel",
      "entreprise": "BankAlMaghrib",
      "ville": "Casablanca",
      "type_contrat": "Contrat à durée indéterminée",
      "experience_requise": null,
      "salaire_brut": "8000-12000 dh",
      "niveau_etudes": "Ingénieur",
      "secteur": "Banque",
      "date_publication": "2024-07-03",
      "date_expiration": "2024-08-02",
      "nb_postes": 2,
      "teletravail": "télétravail",
      "langue_requise": [
        "Français",
        "Anglais"
      ]
    },
    {
      "id_offre": "RK-2024-04753",
      "source": "rekrute",
      "titre_poste": "Data Eng.",
      "description": "Nous recherchons un profil qualifie. Connaissances exigees : Python / SQL / Spark. Travail en equipe Agile.",
      "competences_brut": "React, Node.js, PostgreSQL",
      "entreprise": "DataWize",
      "ville": "Fès",
      "type_contrat": "cdi",
      "experience_requise": null,
      "salaire_brut": "Confidentiel",
      "niveau_etudes": "Bac+5",
      "secteur": "Conseil",
      "date_publication": "2024-07-06",
      "date_expiration": "2024-08-05",
      "nb_postes": 1,
      "teletravail": "télétravail",
      "langue_requise": [
        "Français",
        "Anglais"
      ]
    },
    {
      "id_offre": "RK-2024-04870",
      "source": "rekrute",
      "titre_poste": "DevOps",
      "description": "Nous recherchons un profil qualifie. Connaissances exigees : GCP, BigQuery, Airflow. Travail en equipe Agile.",
      "competences_brut": "Power BI, SQL, Excel",
      "entreprise": "TechMaroc SARL",
      "ville": "Casablanca",
      "type_contrat": "cdi",
      "experience_requise": "min 3 ans",
      "salaire_brut": null,
      "niveau_etudes": "Ingénieur",
      "secteur": "Banque",
      "date_publication": "2024-07-31",
      "date_expiration": "2024-08-30",
      "nb_postes": 1,
      "teletravail": "Hybride",
      "langue_requise": [
        "Français",
        "Anglais"
      ]
    },
    {
      "id_offre": "RK-2024-04952",
      "source": "rekrute",
      "titre_poste": "Développeur BI",
      "description": "Nous recherchons un profil qualifie. Connaissances exigees : GCP, BigQuery, Airflow. Travail en equipe Agile.",
      "competences_brut": "Python / SQL / Spark",
      "entreprise": "TangerMedTech",
      "ville": "Casablanca",
      "type_contrat": "Permanent",
      "experience_requise": "Débutant accepté",
      "salaire_brut": "15000-20000 MAD",
      "niveau_etudes": "Bac+5",
      "secteur": "Informatique / Télécom",
      "date_publication": "2024-07-05",
      "date_expiration": "2024-08-04",
      "nb_postes": 2,
      "teletravail": "Hybride",
      "langue_requise": [
        "Français",
        "Anglais"
      ]
    },
    {
      "id_offre": "RK-2024-04980",
      "source": "rekrute",
      "titre_poste": "Data Engineer Junior",
      "description": "Nous recherchons un profil qualifie. Connaissances exigees : Power BI, SQL, Excel. Travail en equipe Agile.",
      "competences_brut": "React, Node.js, PostgreSQL",
      "entreprise": "TangerMedTech",
      "ville": "Tanger",
      "type_contrat": "CDI",
      "experience_requise": "min 3 ans",
      "salaire_brut": "15000-20000 MAD",
      "niveau_etudes": "Ingénieur",
      "secteur": "Conseil",
      "date_publication": "2024-07-26",
      "date_expiration": "2024-08-25",
      "nb_postes": 2,
      "teletravail": "Présentiel",
      "langue_requise": [
        "Français",
        "Anglais"
      ]
    },
    {
      "id_offre": "RK-2024-00120",
      "source": "rekrute",
      "titre_poste": "Dev Data",
      "description": "Nous recherchons un profil qualifie. Connaissances exigees : Python / SQL / Spark. Travail en equipe Agile.",
      "competences_brut": "GCP, BigQuery, Airflow",
      "entreprise": "DataWize",
      "ville": "casa",
      "type_contrat": "Freelance",
      "experience_requise": "min 3 ans",
      "salaire_brut": "Selon profil",
      "niveau_etudes": "Bac+3",
      "secteur": "Banque",
      "date_publication": "2024-07-13",
      "date_expiration": "2024-08-12",
      "nb_postes": 3,
      "teletravail": "Hybride",
      "langue_requise": [
        "Français",
        "Anglais"
      ]
    },
    {
      "id_offre": "RK-2024-00134",
      "source": "rekrute",
      "titre_poste": "Dev Data",
      "description": "Nous recherchons un profil qualifie. Connaissances exigees : Python / SQL / Spark. Travail en equipe Agile.",
      "competences_brut": "React, Node.js, PostgreSQL",
      "entreprise": "BankAlMaghrib",
      "ville": "CASABLANCA",
      "type_contrat": "CDI",
      "experience_requise": null,
      "salaire_brut": null,
      "niveau_etudes": "Bac+3",
      "secteur": "Informatique / Télécom",
      "date_publication": "2024-07-22",
      "date_expiration": "2024-08-21",
      "nb_postes": 2,
      "teletravail": "Hybride",
      "langue_requise": [
        "Français",
        "Anglais"
      ]
    }
  ]
}